Workbook

Sheet Tổng hợp
A1: TỔNG HỢP KẾT QUẢ KIỂM THỬ
A3: STT | B3: Tên màn hình / Chức năng | C3: Số trường hợp kiểm thử đạt (P) | D3: Số trường hợp kiểm thử không đạt (F) | E3: Số trường hợp kiểm thử đang xem xét (PE) | F3: Số trường hợp kiểm thử chưa thực hiện | G3: Tổng số trường hợp kiểm thử | H3: Tỉ lệ trường hợp kiểm thử đạt (%P) | I3: Tỉ lệ trường hợp kiểm thử không đạt (%F) | J3: Tỉ lệ trường hợp kiểm thử đã thực hiện (%Cover)
A4: 1 | B4: =UPDATE_DB_11G_TO_19C!D2 -> Nâng cấp DB HTDS_VAS 11g -> 19c | C4: =UPDATE_DB_11G_TO_19C!D4 -> 91 | D4: =UPDATE_DB_11G_TO_19C!D5 -> 0 | E4: =UPDATE_DB_11G_TO_19C!D6 -> 0 | F4: =UPDATE_DB_11G_TO_19C!D7 -> 0 | G4: =UPDATE_DB_11G_TO_19C!D8 -> 91 | H4: =C4/G4 -> 1 | I4: =D4/G4 -> 0 | J4: =(C4+D4)/G4 -> 1
A5: Total | C5: =SUM(C4:C4) -> 91 | D5: =SUM(D4:D4) -> 0 | E5: =SUM(E4:E4) -> 0 | F5: =SUM(F4:F4) -> 0 | G5: =SUM(G4:G4) -> 91 | H5: =C4/C5 -> 1 | I5: =D5/G5 -> 0 | J5: =(C5+D5)/G5 -> 1

Sheet UPDATE_DB_11G_TO_19C
C1: KỊCH BẢN KIỂM THỬ
C2: Tên màn hình / Tên chức năng | D2: Nâng cấp DB HTDS_VAS 11g -> 19c
C3: Mã trường hợp kiểm thử | D3: Up_DB
C4: Số trường hợp kiểm thử đạt (P) | D4: =COUNTIF($H$14:$H$3339,"P") -> 91
C5: Số trường hợp kiểm thử không đạt (F) | D5: =COUNTIF($H$14:$H$3339,"F") -> 0
C6: Số trường hợp kiểm thử đang xem xet (PE) | D6: =COUNTIF($H$14:$H$3339,"PE") -> 0
C7: Số trường hợp kiểm thử chưa được thực hiện | D7: =D8-D4-D5-D6 -> 0
C8: Tổng số trường hợp kiểm thử | D8: =COUNTA($D$14:$D$3339) -> 91
A10: Mã trường hợp kiểm thử | B10: Mục đích kiểm thử | C10: Các bước thực hiện | D10: Kết quả mong muốn | E10: Browser Version | H10: Kết quả hiện tại | I10: Mã lỗi | J10: Ghi chú
E11: Lần 1 | F11: Lần 2 | G11: Lần 3
B12: 3.1 Cập nhật file mã hóa tài khoản DB từ Oracle 11g sang Oracle 19c
A14: =IF(AND(D14="",D14=""),"",$D$3&"_"&ROW()-13-COUNTBLANK($D14:D$14)) -> Up_DB_1 | B14: Kiểm tra đường link thư mục chứa file cấu hình | C14: 1. Mở tomcat server test 2. Mở đường link chứa file cấu hình: /u01/app/fmra/htds_vas/htds_webapp/htds_web_deploy/tomcat_xxxx/webapps/HTDS/WEB-INF/classes/com/viettel/htds/config/datasource/ 3. Mở file và decode | D14: Hệ thống hiển thị cấu hình DB đúng với TLGP mô tả | E14: P | F14: P | G14: P | H14: P
B15: 3.2 Nâng cấp thư viện để giao tiếp với Oracle 19c
A16: =IF(AND(D16="",D16=""),"",$D$3&"_"&ROW()-13-COUNTBLANK($D$14:D16)) -> Up_DB_2 | B16: Kiểm tra đường link thư mục chứa file thư viện ojdbc7 | C16: 1. Mở tomcat server test 2. Mở đường link chứa file cấu hình: /u01/app/fmra/htds_vas/htds_webapp/htds_web_deploy/tomcat_xxxx/webapps/HTDS/WEB-INF/classes/com/viettel/htds/config/datasource/ 3. Mở file và decode | D16: Hệ thống hiển thị cấu hình DB đúng với TLGP mô tả | E16: P | F16: P | G16: P | H16: P
B17: 3.5 Cập nhật DB link
B18: Kiểm tra DB Link từ 19c -> 11g - Precondition: đã config DB Link 11g trên DB 19c (HOST = 10.207.222.182 - PORT = 1521 - SERVICE_NAME = DSVAS1)
B19: Kiểm tra kết nối cơ bản
A20: =IF(AND(D20="",D20=""),"",$D$3&"_"&ROW()-13-COUNTBLANK($D$14:D20)) -> Up_DB_3 | B20: Kiểm tra kết nối đơn giản | C20: 1. Mở script tại DB HTDS_VAS 19c 2. Nhập câu lệnh query: -- Test kết nối cơ bản SELECT * FROM dual@link_to_11g; -- Test với user cụ thể SELECT USER FROM dual@link_to_11g; | D20: Hệ thống trả về kết quả sau query: -- Test kết nối cơ bản = X -- Test với user cụ thể = DSVAS | E20: P | F20: P | G20: P | H20: P
A21: =IF(AND(D21="",D21=""),"",$D$3&"_"&ROW()-13-COUNTBLANK($D$14:D21)) -> Up_DB_4 | B21: Kiểm tra thông tin DB Link | C21: 1. Mở script tại DB HTDS_VAS 19c 2. Nhập câu lệnh query: -- Liệt kê tất cả DB Link SELECT db_link, username, host, created FROM all_db_links; -- Kiểm tra DB Link cho user hiện tại SELECT db_link, username, host FROM user_db_links; | D21: Hệ thống trả về kết quả sau query: -- Liệt kê tất cả DB Link = Toàn bộ thông DB link trên DB HTDS_VAS 19c đã đc tạo -- Kiểm tra DB Link cho user hiện tại = Toàn bộ thông DB link trên DB HTDS_VAS 19c đã đc tạo tương ứng với user | E21: P | F21: P | G21: P | H21: P
B22: Kiểm tra truy vấn dữ liệu
A23: =IF(AND(D23="",D23=""),"",$D$3&"_"&ROW()-13-COUNTBLANK($D$14:D23)) -> Up_DB_5 | B23: Kiểm tra truy vấn dữ liệu từ bảng remote | C23: 1. Mở script tại DB HTDS_VAS 19c 2. Nhập câu lệnh query: -- Test truy vấn đơn giản SELECT COUNT(*) FROM CONTRACT@link_to_11g; -- Test với điều kiện WHERE SELECT * FROM CONTRACT@link_to_11g WHERE CONTRACT_ID = 123456; | D23: Hệ thống trả về kết quả sau query: -- Test truy vấn đơn giản = số lượng dữ liệu có trong bảng CONTRACT ở DB HTDS_VAS 11g -- Test với điều kiện WHERE = hiển thị dữ liệu tương ứng với CONTRACT_ID = 123456 ở DB HTDS_VAS 11g | E23: P | F23: P | G23: P | H23: P
A24: =IF(AND(D24="",D24=""),"",$D$3&"_"&ROW()-13-COUNTBLANK($D$14:D24)) -> Up_DB_6 | B24: Kiểm tra hiệu suất truy vấn từ bảng remote | C24: 1. Mở script tại DB HTDS_VAS 19c 2. Nhập câu lệnh query: -- Đo thời gian truy vấn SELECT COUNT(*) FROM IC_REPORT_DETAIL@link_to_11g | D24: Hệ thống trả về kết quả sau query: -- Đo thời gian truy vấn: Với dữ liệu khoảng 10k mất ~ 100ms (tức khá nhanh) | E24: P | F24: P | G24: P | H24: P
B25: Kiểm tra thay đổi dữ liệu trong bảng
A26: =IF(AND(D26="",D26=""),"",$D$3&"_"&ROW()-13-COUNTBLANK($D$14:D26)) -> Up_DB_7 | B26: Kiểm tra INSERT qua DB Link | C26: 1. Mở script tại DB HTDS_VAS 19c 2. Nhập câu lệnh query: -- Test INSERT INSERT INTO DB19CTEST@link_to_11g (test_id, test_name, test_no, test_category) VALUES ('79', 'LUCKY_NUMBER', '79.79', 'Số thần tài lớn'); -- Kiểm tra dữ liệu sau khi đã insert SELECT * FROM DB19CTEST@link_to_11g WHERE TEST_ID = '79'; -- Rollback để không ảnh hưởng dữ liệu cũ ROLLBACK; | D26: Hệ thống trả về kết quả sau query: -- Test INSERT : Thông báo insert thành công 1 bản ghi -- Kiểm tra dữ liệu sau khi đã insert: Hệ thống hiển thị dữ liệu tương ứng đã insert trong bảng | E26: P | F26: P | G26: P | H26: P
A27: =IF(AND(D27="",D27=""),"",$D$3&"_"&ROW()-13-COUNTBLANK($D$14:D27)) -> Up_DB_8 | B27: Kiểm tra UPDATE qua DB Link | C27: 1. Mở script tại DB HTDS_VAS 19c 2. Nhập câu lệnh query: -- Test UPDATE UPDATE DB19CTEST@link_to_11g SET TEST_NO = '79.179' WHERE TEST_ID = '79'; -- Kiểm tra kết quả SELECT * FROM DB19CTEST@link_to_11g WHERE TEST_ID = '79'; -- Rollback để không ảnh hưởng dữ liệu cũ ROLLBACK; | D27: Hệ thống trả về kết quả sau query: -- Test UPDATE : Thông báo update thành công 1 bản ghi -- Kiểm tra dữ liệu sau khi đã update: Hệ thống hiển thị dữ liệu tương ứng đã và dữ liệu update đúng trong bảng | E27: P | F27: P | G27: P | H27: P
A28: =IF(AND(D28="",D28=""),"",$D$3&"_"&ROW()-13-COUNTBLANK($D$14:D28)) -> Up_DB_9 | B28: Kiểm tra DELETE qua DB Link | C28: 1. Mở script tại DB HTDS_VAS 19c 2. Nhập câu lệnh query: -- Test DETELE DELETE FROM DB19CTEST@link_to_11g WHERE TEST_ID = '79'; -- Kiểm tra kết quả SELECT * FROM DB19CTEST@link_to_11g WHERE TEST_ID = '79'; -- Rollback để không ảnh hưởng dữ liệu cũ ROLLBACK; | D28: Hệ thống trả về kết quả sau query: -- Test DELETE : Thông báo delete thành công 1 bản ghi -- Kiểm tra dữ liệu sau khi đã delete: Hệ thống ko hiển thị dữ liệu vì đã bị xóa trong bảng | E28: P | F28: P | G28: P | H28: P
B29: Kiểm tra thay đổi dữ liệu bảng
A30: =IF(AND(D30="",D30=""),"",$D$3&"_"&ROW()-13-COUNTBLANK($D$14:D30)) -> Up_DB_10 | B30: Kiểm tra CREATE TABLE qua DB link | C30: 1. Mở script tại DB HTDS_VAS 19c 2. Nhập câu lệnh query: -- Test CREATE bảng CREATE TABLE DB19cTEST@link_to_11g ( test_id NUMBER PRIMARY KEY, test_name VARCHAR2(100) NOT NULL, test_no NUMBER(10,2) NOT NULL, test_category VARCHAR2(50) ); -- Kiểm tra kết quả SELECT * FROM rDB19cTEST@link_to_11g; | D30: Hệ thống trả về kết quả sau query: Bảng DB19CTEST vơi các cột dữ liệu như đã khai báo Kiểm tra chi tiết về kiểu dữ liệu: Dbeaver hiển thị kiểu dữ liệu của từng cột trong bảng đúng như đã khai báo | E30: P | F30: P | G30: P | H30: P
A31: =IF(AND(D31="",D31=""),"",$D$3&"_"&ROW()-13-COUNTBLANK($D$14:D31)) -> Up_DB_11 | B31: Kiểm tra ALERT TABLE qua DB link | C31: 1. Mở script tại DB HTDS_VAS 19c 2. Nhập câu lệnh query: -- Test ALERT bảng ALTER TABLE DB19cTEST@link_to_11g ADD (description VARCHAR2(500)); -- Kiểm tra kết quả SELECT * FROM rDB19cTEST@link_to_11g; | D31: Hệ thống trả về kết quả sau query: Bảng DB19CTEST có thêm cột DESCRIPTION, các cột khác được giữ nguyên Kiểm tra chi tiết về kiểu dữ liệu: Dbeaver hiển thị kiểu dữ liệu cột DESCRIPTION đúng như đã khai báo, các cột khác ko có gì thay đổi | E31: P | F31: P | G31: P | H31: P
A32: =IF(AND(D32="",D32=""),"",$D$3&"_"&ROW()-13-COUNTBLANK($D$14:D32)) -> Up_DB_12 | B32: Kiểm tra TRUNCATE TABLE qua DB link | C32: 1. Mở script tại DB HTDS_VAS 19c - Pre: Bảng DB19cTEST đã có dữ liệu 2. Nhập câu lệnh query: -- Test TRUNCATE TRUNCATE TABLE DB19cTEST@link_to_11g; -- Kiểm tra kết quả SELECT * FROM rDB19cTEST@link_to_11g; | D32: Hệ thống trả về kết quả sau query: Bảng DB19CTEST không có dòng dữ liệu nào, cấu trúc bảng được giữ nguyên | E32: P | F32: P | G32: P | H32: P
A33: =IF(AND(D33="",D33=""),"",$D$3&"_"&ROW()-13-COUNTBLANK($D$14:D33)) -> Up_DB_13 | B33: Kiểm tra DROP TABLE qua DB link | C33: 1. Mở script tại DB HTDS_VAS 19c 2. Nhập câu lệnh query: -- Test DROP DROP TABLE DB19cTEST@link_to_11g; -- Kiểm tra kết quả SELECT * FROM rDB19cTEST@link_to_11g; | D33: Hệ thống trả về kết quả sau query: Báo lỗi không có bảng DB19CTEST không tồn tại ~ xóa hoàn toàn bảng khỏi DB | E33: P | F33: P | G33: P | H33: P
B34: Kiểm tra các kịch bản sẽ báo lỗi
A35: =IF(AND(D35="",D35=""),"",$D$3&"_"&ROW()-13-COUNTBLANK($D$14:D35)) -> Up_DB_14 | B35: Kiểm tra DB Link không tồn tại | C35: 1. Mở script tại DB HTDS_VAS 19c 2. Nhập câu lệnh query: -- Test với DB Link không tồn tại SELECT * FROM dual@abc_123_abc_456; | D35: Hệ thống trả về kết quả sau query: Báo lỗi không tồn tại DB link abc_123_abc_456 | E35: P | F35: P | G35: P | H35: P
A36: =IF(AND(D36="",D36=""),"",$D$3&"_"&ROW()-13-COUNTBLANK($D$14:D36)) -> Up_DB_15 | B36: Kiểm tra table trong DB Link không tồn tại | C36: 1. Mở script tại DB HTDS_VAS 19c 2. Nhập câu lệnh query: -- Test với table không tồn tại SELECT * FROM 112233abcdef@link_to_11g; | D36: Hệ thống trả về kết quả sau query: Báo lỗi không tồn tại bảng 112233abcdef | E36: P | F36: P | G36: P | H36: P
A37: =IF(AND(D37="",D37=""),"",$D$3&"_"&ROW()-13-COUNTBLANK($D$14:D37)) -> Up_DB_16 | B37: Kiểm tra table trong DB Link không được cấp quyền truy cập | C37: 1. Mở script tại DB HTDS_VAS 19c 2. Nhập câu lệnh query: -- Test với table không tồn tại SELECT * FROM …...@link_to_11g; | D37: Hệ thống trả về kết quả sau query: Báo lỗi không có quyền truy cập bảng….. | E37: P | F37: P | G37: P | H37: P
B38: Kiểm tra đồng bộ dữ liệu
A39: =IF(AND(D39="",D39=""),"",$D$3&"_"&ROW()-13-COUNTBLANK($D$14:D39)) -> Up_DB_17 | B39: Kiểm tra số lượng bản ghi đang tồn tại | C39: 1. Mở script tại DB HTDS_VAS 19c 2. Nhập câu lệnh query: SELECT COUNT(*) as count FROM CONTRACT UNION ALL SELECT COUNT(*) as count FROM CONTRACT@link_to_11g; | D39: Hệ thống trả về 2 kết quả và so sánh - Nếu DB mới build và mới đồng bộ mà: + DB gốc > DB link -> mất dự liệu khi đồng bộ + DB gốc = DB link: Dữ liệu đc đồng bộ hoàn toàn + DB gốc < DB link -> dự liệu bị xử lý sai lệch/thừa khi đồng bộ - Nếu DB đã build lâu và đã thao tác tác động tới DB: 2 kết quả bình thường, không phản ánh được đúng sai của tiến trình đồng bộ | E39: P | F39: P | G39: P | H39: P
A40: =IF(AND(D40="",D40=""),"",$D$3&"_"&ROW()-13-COUNTBLANK($D$14:D40)) -> Up_DB_18 | B40: Kiểm tra và so sánh dữ liệu cụ thể | C40: 1. Mở script tại DB HTDS_VAS 19c 2. Nhập câu lệnh query: SELECT c.*, r.* FROM CONTRACT c FULL OUTER JOIN CONTRACT@link_to_11g r ON c.CONTRACT_ID = r.CONTRACT_ID; | D40: Hệ thống trả về kết quả sau khi query: Trả về toàn bộ dữ liệu phù hợp với điều kiện join, chọn bất 1 dòng dữ liệu ko bị sửa rồi (hoặc ngay sau khi đồng bộ) thì data trả về từ bảng gốc và bảng remote giống nhau hoàn toàn | E40: P | F40: P | G40: P | H40: P
B41: Kiểm tra DB Link từ 11g -> 19c - Precondition: đã config DB Link 19c trên DB 11g (HOST = 10.207.222.143 - PORT = 9000 - SERVICE_NAME = DSVAS1)
B42: Kiểm tra kết nối cơ bản
A43: =IF(AND(D43="",D43=""),"",$D$3&"_"&ROW()-13-COUNTBLANK($D$14:D43)) -> Up_DB_19 | B43: Kiểm tra kết nối đơn giản | C43: 1. Mở script tại DB HTDS_VAS 11g 2. Nhập câu lệnh query: -- Test kết nối cơ bản SELECT * FROM dual@link_to_19c; -- Test với user cụ thể SELECT USER FROM dual@link_to_19c; | D43: Hệ thống trả về kết quả sau query: -- Test kết nối cơ bản = X -- Test với user cụ thể = DSVAS | E43: P | F43: P | G43: P | H43: P
A44: =IF(AND(D44="",D44=""),"",$D$3&"_"&ROW()-13-COUNTBLANK($D$14:D44)) -> Up_DB_20 | B44: Kiểm tra thông tin DB Link | C44: 1. Mở script tại DB HTDS_VAS 11g 2. Nhập câu lệnh query: -- Liệt kê tất cả DB Link SELECT db_link, username, host, created FROM all_db_links; -- Kiểm tra DB Link cho user hiện tại SELECT db_link, username, host FROM user_db_links; | D44: Hệ thống trả về kết quả sau query: -- Liệt kê tất cả DB Link = Toàn bộ thông DB link trên DB HTDS_VAS 11g đã đc tạo -- Kiểm tra DB Link cho user hiện tại = Toàn bộ thông DB link trên DB HTDS_VAS 11g đã đc tạo tương ứng với user | E44: P | F44: P | G44: P | H44: P
B45: Kiểm tra truy vấn dữ liệu
A46: =IF(AND(D46="",D46=""),"",$D$3&"_"&ROW()-13-COUNTBLANK($D$14:D46)) -> Up_DB_21 | B46: Kiểm tra truy vấn dữ liệu từ bảng remote | C46: 1. Mở script tại DB HTDS_VAS 11g 2. Nhập câu lệnh query: -- Test truy vấn đơn giản SELECT COUNT(*) FROM CONTRACT@link_to_19c; -- Test với điều kiện WHERE SELECT * FROM CONTRACT@link_to_19c WHERE CONTRACT_ID = 123456; | D46: Hệ thống trả về kết quả sau query: -- Test truy vấn đơn giản = số lượng dữ liệu có trong bảng CONTRACT ở DB HTDS_VAS 19c -- Test với điều kiện WHERE = hiển thị dữ liệu tương ứng với CONTRACT_ID = 123456 ở DB HTDS_VAS 19c | E46: P | F46: P | G46: P | H46: P
A47: =IF(AND(D47="",D47=""),"",$D$3&"_"&ROW()-13-COUNTBLANK($D$14:D47)) -> Up_DB_22 | B47: Kiểm tra hiệu suất truy vấn từ bảng remote | C47: 1. Mở script tại DB HTDS_VAS 11g 2. Nhập câu lệnh query: -- Đo thời gian truy vấn SELECT COUNT(*) FROM IC_REPORT_DETAIL@link_to_19c | D47: Hệ thống trả về kết quả sau query: -- Đo thời gian truy vấn: Với dữ liệu khoảng 10k mất ~ 100ms (tức khá nhanh) | E47: P | F47: P | G47: P | H47: P
B48: Kiểm tra thay đổi dữ liệu trong bảng
A49: =IF(AND(D49="",D49=""),"",$D$3&"_"&ROW()-13-COUNTBLANK($D$14:D49)) -> Up_DB_23 | B49: Kiểm tra INSERT qua DB Link | C49: 1. Mở script tại DB HTDS_VAS 11g 2. Nhập câu lệnh query: -- Test INSERT INSERT INTO DB19CTEST@link_to_19c (test_id, test_name, test_no, test_category) VALUES ('79', 'LUCKY_NUMBER', '79.79', 'Số thần tài lớn'); -- Kiểm tra dữ liệu sau khi đã insert SELECT * FROM DB11GTEST@link_to_19c WHERE TEST_ID = '79'; -- Rollback để không ảnh hưởng dữ liệu cũ ROLLBACK; | D49: Hệ thống trả về kết quả sau query: -- Test INSERT : Thông báo insert thành công 1 bản ghi -- Kiểm tra dữ liệu sau khi đã insert: Hệ thống hiển thị dữ liệu tương ứng đã insert trong bảng | E49: P | F49: P | G49: P | H49: P
A50: =IF(AND(D50="",D50=""),"",$D$3&"_"&ROW()-13-COUNTBLANK($D$14:D50)) -> Up_DB_24 | B50: Kiểm tra UPDATE qua DB Link | C50: 1. Mở script tại DB HTDS_VAS 11g 2. Nhập câu lệnh query: -- Test UPDATE UPDATE DB19CTEST@link_to_19c SET TEST_NO = '79.179' WHERE TEST_ID = '79'; -- Kiểm tra dữ liệu sau khi đã update SELECT * FROM DB11GTEST@link_to_19c WHERE TEST_ID = '79'; -- Rollback để không ảnh hưởng dữ liệu cũ ROLLBACK; | D50: Hệ thống trả về kết quả sau query: -- Test UPDATE : Thông báo update thành công 1 bản ghi -- Kiểm tra dữ liệu sau khi đã update: Hệ thống hiển thị dữ liệu tương ứng đã và dữ liệu update đúng trong bảng | E50: P | F50: P | G50: P | H50: P
A51: =IF(AND(D51="",D51=""),"",$D$3&"_"&ROW()-13-COUNTBLANK($D$14:D51)) -> Up_DB_25 | B51: Kiểm tra DELETE qua DB Link | C51: 1. Mở script tại DB HTDS_VAS 11g 2. Nhập câu lệnh query: -- Test DETELE DELETE FROM DB19CTEST@link_to_19c WHERE TEST_ID = '79'; -- Kiểm tra dữ liệu sau khi đã delete SELECT * FROM DB11GTEST@link_to_19c WHERE TEST_ID = '79'; -- Rollback để không ảnh hưởng dữ liệu cũ ROLLBACK; | D51: Hệ thống trả về kết quả sau query: -- Test DELETE : Thông báo delete thành công 1 bản ghi -- Kiểm tra dữ liệu sau khi đã delete: Hệ thống ko hiển thị dữ liệu vì đã bị xóa trong bảng | E51: P | F51: P | G51: P | H51: P
B52: Kiểm tra thay đổi dữ liệu bảng
A53: =IF(AND(D53="",D53=""),"",$D$3&"_"&ROW()-13-COUNTBLANK($D$14:D53)) -> Up_DB_26 | B53: Kiểm tra CREATE TABLE qua DB link | C53: 1. Mở script tại DB HTDS_VAS 11g 2. Nhập câu lệnh query: -- Test CREATE bảng CREATE TABLE DB11GTEST@link_to_19c ( test_id NUMBER PRIMARY KEY, test_name VARCHAR2(100) NOT NULL, test_no NUMBER(10,2) NOT NULL, test_category VARCHAR2(50) ); -- Kiểm tra kết quả SELECT * FROM rDB11GTEST@link_to_19c; | D53: Hệ thống trả về kết quả sau query: Bảng DB11GTEST vơi các cột dữ liệu như đã khai báo Kiểm tra chi tiết về kiểu dữ liệu: Dbeaver hiển thị kiểu dữ liệu của từng cột trong bảng đúng như đã khai báo | E53: P | F53: P | G53: P | H53: P
A54: =IF(AND(D54="",D54=""),"",$D$3&"_"&ROW()-13-COUNTBLANK($D$14:D54)) -> Up_DB_27 | B54: Kiểm tra ALERT TABLE qua DB link | C54: 1. Mở script tại DB HTDS_VAS 11g 2. Nhập câu lệnh query: -- Test ALERT bảng ALTER TABLE DB19cTEST@link_to_19c ADD (description VARCHAR2(500)); -- Kiểm tra kết quả SELECT * FROM rDB11GTEST@link_to_19c; | D54: Hệ thống trả về kết quả sau query: Bảng DB19CTEST có thêm cột DESCRIPTION, các cột khác được giữ nguyên Kiểm tra chi tiết về kiểu dữ liệu: Dbeaver hiển thị kiểu dữ liệu cột DESCRIPTION đúng như đã khai báo, các cột khác ko có gì thay đổi | E54: P | F54: P | G54: P | H54: P
A55: =IF(AND(D55="",D55=""),"",$D$3&"_"&ROW()-13-COUNTBLANK($D$14:D55)) -> Up_DB_28 | B55: Kiểm tra TRUNCATE TABLE qua DB link | C55: 1. Mở script tại DB HTDS_VAS 11g - Pre: Bảng DB19cTEST đã có dữ liệu 2. Nhập câu lệnh query: -- Test TRUNCATE TRUNCATE TABLE DB19cTEST@link_to_19c; -- Kiểm tra kết quả SELECT * FROM rDB11GTEST@link_to_19c; | D55: Hệ thống trả về kết quả sau query: Bảng DB19CTEST không có dòng dữ liệu nào, cấu trúc bảng được giữ nguyên | E55: P | F55: P | G55: P | H55: P
A56: =IF(AND(D56="",D56=""),"",$D$3&"_"&ROW()-13-COUNTBLANK($D$14:D56)) -> Up_DB_29 | B56: Kiểm tra DROP TABLE qua DB link | C56: 1. Mở script tại DB HTDS_VAS 11g 2. Nhập câu lệnh query: -- Test DROP DROP TABLE DB19cTEST@link_to_19c; -- Kiểm tra kết quả SELECT * FROM rDB11GTEST@link_to_19c; | D56: Hệ thống trả về kết quả sau query: Báo lỗi không có bảng DB19CTEST không tồn tại ~ xóa hoàn toàn bảng khỏi DB | E56: P | F56: P | G56: P | H56: P
B57: Kiểm tra các kịch bản sẽ báo lỗi
A58: =IF(AND(D58="",D58=""),"",$D$3&"_"&ROW()-13-COUNTBLANK($D$14:D58)) -> Up_DB_30 | B58: Kiểm tra DB Link không tồn tại | C58: 1. Mở script tại DB HTDS_VAS 11g 2. Nhập câu lệnh query: -- Test với DB Link không tồn tại SELECT * FROM dual@abc_123_abc_456; | D58: Hệ thống trả về kết quả sau query: Báo lỗi không tồn tại DB link abc_123_abc_456 | E58: P | F58: P | G58: P | H58: P
A59: =IF(AND(D59="",D59=""),"",$D$3&"_"&ROW()-13-COUNTBLANK($D$14:D59)) -> Up_DB_31 | B59: Kiểm tra table trong DB Link không tồn tại | C59: 1. Mở script tại DB HTDS_VAS 11g 2. Nhập câu lệnh query: -- Test với table không tồn tại SELECT * FROM 112233abcdef@link_to_19c; | D59: Hệ thống trả về kết quả sau query: Báo lỗi không tồn tại bảng 112233abcdef | E59: P | F59: P | G59: P | H59: P
A60: =IF(AND(D60="",D60=""),"",$D$3&"_"&ROW()-13-COUNTBLANK($D$14:D60)) -> Up_DB_32 | B60: Kiểm tra table trong DB Link không được cấp quyền truy cập | C60: 1. Mở script tại DB HTDS_VAS 11g 2. Nhập câu lệnh query: -- Test với table không tồn tại SELECT * FROM …...@link_to_19c; | D60: Hệ thống trả về kết quả sau query: Báo lỗi không có quyền truy cập bảng….. | E60: P | F60: P | G60: P | H60: P
B61: Kiểm tra đồng bộ dữ liệu
A62: =IF(AND(D62="",D62=""),"",$D$3&"_"&ROW()-13-COUNTBLANK($D$14:D62)) -> Up_DB_33 | B62: Kiểm tra số lượng bản ghi đang tồn tại | C62: 1. Mở script tại DB HTDS_VAS 11g 2. Nhập câu lệnh query: SELECT COUNT(*) as count FROM CONTRACT UNION ALL SELECT COUNT(*) as count FROM CONTRACT@link_to_19c; | D62: Hệ thống trả về 2 kết quả và so sánh - Nếu DB mới build và mới đồng bộ mà: + DB gốc > DB link -> mất dự liệu khi đồng bộ + DB gốc = DB link: Dữ liệu đc đồng bộ hoàn toàn + DB gốc < DB link -> dự liệu bị xử lý sai lệch/thừa khi đồng bộ - Nếu DB đã build lâu và đã thao tác tác động tới DB: 2 kết quả bình thường, không phản ánh được đúng sai của tiến trình đồng bộ | E62: P | F62: P | G62: P | H62: P
A63: =IF(AND(D63="",D63=""),"",$D$3&"_"&ROW()-13-COUNTBLANK($D$14:D63)) -> Up_DB_34 | B63: Kiểm tra và so sánh dữ liệu cụ thể | C63: 1. Mở script tại DB HTDS_VAS 11g 2. Nhập câu lệnh query: SELECT c.*, r.* FROM CONTRACT c FULL OUTER JOIN CONTRACT@link_to_19c r ON c.CONTRACT_ID = r.CONTRACT_ID; | D63: Hệ thống trả về kết quả sau khi query: Trả về toàn bộ dữ liệu phù hợp với điều kiện join, chọn bất 1 dòng dữ liệu ko bị sửa rồi (hoặc ngay sau khi đồng bộ) thì data trả về từ bảng gốc và bảng remote giống nhau hoàn toàn | E63: P | F63: P | G63: P | H63: P
B64: 3.6 Danh sách hệ thống và tiến trình bị ảnh hưởng
B65: 3.6.1. /u01/doisoat/tomcat_vsa_8568: VSA của portal Đăng nhập thành công bằng tài khoản admin hệ thống (sys/We****10)
B66: Sự kiện Tìm kiếm -> truy vấn trong DB tương ứng
A67: =IF(AND(D67="",D67=""),"",$D$3&"_"&ROW()-13-COUNTBLANK($D$14:D67)) -> Up_DB_35 | B67: Tìm kiếm tại màn hình User -> Manage user | C67: 1. Truy cập màn hình Manage User -> Tìm kiếm all 2. Truy cập DB và query bảng USERS select * from USERS; | D67: Các bản ghi hiển thị tại Data Grid trùng khớp với DB trả về cả số lượng và dữ liệu | E67: P | F67: P | G67: P | H67: P
B68: Các sự kiện Thêm mới, Xóa, Sửa dữ liệu tại các màn hình dẫn tới sự kiện thay đổi trên DB bảng tương ứng
A69: =IF(AND(D69="",D69=""),"",$D$3&"_"&ROW()-13-COUNTBLANK($D$14:D69)) -> Up_DB_36 | B69: Thêm mới bản ghi tại màn hình User -> Manage user type | C69: 1. Truy cập màn hình Manage User Type -> Thực hiện thêm mới thành công 1 bản ghi bất kỳ (nhập dữ liệu hợp lệ) 2. Truy cập DB và query bảng USER_TYPE; select * from USER_TYPE; | D69: Bản ghi mới được thêm vào bảng USER_TYPE với dữ liệu đúng như đã nhập trên UI | E69: P | F69: P | G69: P | H69: P
A70: =IF(AND(D70="",D70=""),"",$D$3&"_"&ROW()-13-COUNTBLANK($D$14:D70)) -> Up_DB_37 | B70: Xóa bản ghi tại màn hình User -> Manage user type | C70: 1. Truy cập màn hình Manage User Type -> Thực hiện xóa bản ghi vừa được thêm mới ở trên 2. Truy cập DB và query bảng USER_TYPE; select * from USER_TYPE; | D70: Bản ghi mới được thêm vào bảng USER_TYPE đã được xóa khỏi bảng, trên UI cũng không còn hiển thị bản ghi đó | E70: P | F70: P | G70: P | H70: P
B71: 3.6.2. /u01/doisoat/new_tomcat_VSA/new_tomcat_passport_8566/test_passport_8566_tomcat7: passport của portal (103+104)
A72: =IF(AND(D72="",D72=""),"",$D$3&"_"&ROW()-13-COUNTBLANK($D$14:D72)) -> Up_DB_38 | B72: Kiểm tra khi có bất kỳ sự kiện thay đổi nào ở VSA portal | C72: 1. Truy cập link passport của PORTAL 2. Thực hiện thay đổi (thêm mới, sửa, xóa,…) trên VSA portal 3. Truy cập lại PORTAL | D72: Hệ thống yêu cầu refresh lại trang passport | E72: P | F72: P | G72: P | H72: P
A73: =IF(AND(D73="",D73=""),"",$D$3&"_"&ROW()-13-COUNTBLANK($D$14:D73)) -> Up_DB_39 | B73: Kiểm tra đăng nhập portal với tài khoản có quyền truy cập đầy đủ | C73: 1. Truy cập link passport của PORTAL 2. Nhập thông tin tài khoản và đăng nhập | D73: Hệ thống validate và access cho phép đăng nhập vào hệ thống portal | E73: P | F73: P | G73: P | H73: P
A74: =IF(AND(D74="",D74=""),"",$D$3&"_"&ROW()-13-COUNTBLANK($D$14:D74)) -> Up_DB_40 | B74: Kiểm tra đăng nhập portal và truy cập tính năng bất kỳ để thực hiện tìm kiếm | C74: 1. Truy cập link passport của PORTAL 2. Truy cập PORTAL bằng tài khoản (dt_nhanvien) 3. Kiểm tra | D74: Tài khoản dt_nhanvien đang được gắn cho đối tác BIDV_1900 (partner_id = 54887) Thực hiện tìm kiếm bất kỳ ở màn nào VD: Menu -> Quản lý đối soát chính thức -> Nhân viên đối tác xác nhận-đối soát chính thức. Thực hiện tìm kiếm All thì sẽ hiển thị ra các BBCT có đối tác là BIDV_1900 ở tại tất cả các kỳ | E74: P | F74: P | G74: P | H74: P
B75: 3.6.3. /u01/doisoat/htds_web_deploy/tomcat_8756 : webapp (103+104)
B76: Sự kiện Tìm kiếm -> truy vấn trong DB tương ứng
A77: =IF(AND(D77="",D77=""),"",$D$3&"_"&ROW()-13-COUNTBLANK($D$14:D77)) -> Up_DB_41 | B77: Kiểm tra màn hình Luồng công việc theo Hợp Đồng (hệ thống tự động tìm kiếm và fill sẵn kết quả lên Data grid) | C77: 1. Truy cập màn hình mặc định 2. Kiểm tra Data grid Danh sách luồng công việc đối chiếu với WORK_FLOW_TYPE được khai báo tại màn App_params 3. Thực hiện truy vấn trên DB và đối chiếu các bản ghi select * from WORK_FLOW; | D77: Các bản ghi tại danh sách trên màn hình và dữ liệu được DB trả về khớp nhau | E77: P | F77: P | G77: P | H77: P | J77: Thực hiện kiểm tra thêm với các màn hình khác và các tiêu chí khác để tăng nhiều mẫu thử
A78: =IF(AND(D78="",D78=""),"",$D$3&"_"&ROW()-13-COUNTBLANK($D$14:D78)) -> Up_DB_42 | C78: 1. Chọn 1 luồng công việc bất kỳ (VD: Luồng đối soát đơn vị ngoài - STT 16) 2. Click Tab Chi tiết luồng công việc, kiểm tra Data grid các bước của luồng công việc đối chiếu với IC_REPORT_STATUS_EXT được khai báo tại màn App_params với các giá trị tương ứng 3. Thực hiện truy vấn trên DB và đối chiếu các bản ghi select * from WORK_FLOW_DETAIL where WORD_FLOW_ID = 407 (ID của luồng công việc đã chọn) | D78: Các bản ghi tại danh sách trên màn hình và dữ liệu được DB trả về khớp nhau (giá trị theo từng step khớp nhau và ID tăng dần theo mỗi step tương ứng với việc sắp xếp trên UI) | E78: P | F78: P | G78: P | H78: P
A79: =IF(AND(D79="",D79=""),"",$D$3&"_"&ROW()-13-COUNTBLANK($D$14:D79)) -> Up_DB_43 | B79: Kiểm tra màn hình Giao hợp đồng cho nhân viên kiểm tra xác nhận (Thực hiện nhập tiêu chí tìm kiếm và bản ghi được trả về tại Data grid) | C79: 1. Truy cập màn hình mặc định 2. Nhập thông tin tìm kiếm -> Click [Tìm kiếm] -> Kiểm tra Data grid [Danh sách nhân viên] VD: - Đối tác = YEAH1 - Phòng ban = Phòng đối soát - Trạng thái = Tất cả - Trạng thái khóa = Tất cả - Loại công việc = Tất cả - Trạng thái công việc = Tất cả 3. Thực hiện truy vấn trên DB và đối chiếu bản ghi select * from CONTRACT_STAFF where DEPT_ID = 11 and CONTRACT_ID in (select CONTRACT_ID from CONTRACT where PARTNER_ID in (select PARTNER_ID from PARTNER where CODE = 'YEAH1')); | D79: Các bản ghi tại danh sách trên màn hình và dữ liệu được DB trả về khớp nhau (như VD Data grid rỗng và trên DB cũng rỗng) | E79: P | F79: P | G79: P | H79: P
B80: Các sự kiện Thêm mới, Xóa, Sửa dữ liệu tại các màn hình dẫn tới sự kiện thay đổi trên DB bảng tương ứng
A81: =IF(AND(D81="",D81=""),"",$D$3&"_"&ROW()-13-COUNTBLANK($D$14:D81)) -> Up_DB_44 | B81: Kiểm tra màn hình Danh mục Dịch vụ/Biểu mẫu/Mẫu jasper/Mẫu SQL với DB bảng SERVICES / TEMPLATE / TEMPLTAE_JASPER | C81: 1. Thêm mới thành công 1 dịch vụ mới 2. Kiểm tra DB bảng SERVICES Select * from SERVICES where CODE = '…Mã dịch vụ thêm mới ….' | D81: DB trả về dữ liệu đúng như đã thêm mới | E81: P | F81: P | G81: P | H81: P | J81: Thực hiện kiểm tra thêm với các màn hình khác và nhiều dữ liệu đc input hơn để tăng mẫu thử
A82: =IF(AND(D82="",D82=""),"",$D$3&"_"&ROW()-13-COUNTBLANK($D$14:D82)) -> Up_DB_45 | C82: 1. Sửa thành công 1 dịch vụ bất kỳ 2. Kiểm tra DB bảng SERVICES Select * from SERVICES where CODE = '…Mã dịch vụ đã sửa ….' | D82: DB trả về dữ liệu đúng như đã sửa | E82: P | F82: P | G82: P | H82: P
A83: =IF(AND(D83="",D83=""),"",$D$3&"_"&ROW()-13-COUNTBLANK($D$14:D83)) -> Up_DB_46 | C83: 1. Xóa thành công 1 dịch vụ bất kỳ 2. Kiểm tra DB bảng SERVICES Select * from SERVICES where CODE = '…Mã dịch vụ đã xóa….' | D83: DB trả về rỗng -> dữ liệu đã đc hóa thành công | E83: P | F83: P | G83: P | H83: P
A84: =IF(AND(D84="",D84=""),"",$D$3&"_"&ROW()-13-COUNTBLANK($D$14:D84)) -> Up_DB_47 | C84: 1. Thêm mới thành công 1 dịch vụ mới 2. Kiểm tra DB bảng TEMPLATE Select * from TEMPLATE where CODE = '…Mã template thêm mới ….' | D84: DB trả về dữ liệu đúng như đã thêm mới | E84: P | F84: P | G84: P | H84: P
A85: =IF(AND(D85="",D85=""),"",$D$3&"_"&ROW()-13-COUNTBLANK($D$14:D85)) -> Up_DB_48 | C85: 1. Sửa thành công 1 dịch vụ bất kỳ 2. Kiểm tra DB bảng TEMPLATE Select * from TEMPLATE where CODE = '…Mã template đã sửa ….' | D85: DB trả về dữ liệu đúng như đã sửa | E85: P | F85: P | G85: P | H85: P
A86: =IF(AND(D86="",D86=""),"",$D$3&"_"&ROW()-13-COUNTBLANK($D$14:D86)) -> Up_DB_49 | C86: 1. Xóa thành công 1 dịch vụ bất kỳ 2. Kiểm tra DB bảng STEMPLATE Select * from TEMPLATE where CODE = '…Mã template đã xóa….' | D86: DB trả về rỗng -> dữ liệu đã đc hóa thành công | E86: P | F86: P | G86: P | H86: P
A87: =IF(AND(D87="",D87=""),"",$D$3&"_"&ROW()-13-COUNTBLANK($D$14:D87)) -> Up_DB_50 | C87: 1. Thêm mới thành công 1 dịch vụ mới 2. Kiểm tra DB bảng TEMPLTAE_JASPER Select * from TEMPLTAE_JASPER where CODE = '…Mã jasper thêm mới ….' | D87: DB trả về dữ liệu đúng như đã thêm mới | E87: P | F87: P | G87: P | H87: P
A88: =IF(AND(D88="",D88=""),"",$D$3&"_"&ROW()-13-COUNTBLANK($D$14:D88)) -> Up_DB_51 | C88: 1. Sửa thành công 1 dịch vụ bất kỳ 2. Kiểm tra DB bảng TEMPLTAE_JASPER Select * from TEMPLTAE_JASPER where CODE = '…Mã jasper đã sửa ….' | D88: DB trả về dữ liệu đúng như đã sửa | E88: P | F88: P | G88: P | H88: P
A89: =IF(AND(D89="",D89=""),"",$D$3&"_"&ROW()-13-COUNTBLANK($D$14:D89)) -> Up_DB_52 | C89: 1. Xóa thành công 1 dịch vụ bất kỳ 2. Kiểm tra DB bảng TEMPLTAE_JASPER Select * from TEMPLTAE_JASPER where CODE = '…Mã jasper đã xóa….' | D89: DB trả về rỗng -> dữ liệu đã đc hóa thành công | E89: P | F89: P | G89: P | H89: P
A90: =IF(AND(D90="",D90=""),"",$D$3&"_"&ROW()-13-COUNTBLANK($D$14:D90)) -> Up_DB_53 | B90: Kiểm tra màn hình Quản lý Phiếu yêu cầu, thực hiện hoàn chỉnh 1 PYC Demo từ đầu đến cuối | C90: 1. Thêm mới thành công 1 bản ghi vào Data grid Danh sách Phiếu yêu cầu ở Tab Thông tin chung 2. Kiểm tra DB bảng REQUIREMENT_FORM select * from REQUIREMENT_FORM where NAME = '…Tên PYC…' | D90: DB trả về dữ liệu đúng như đã thêm mới | E90: P | F90: P | G90: P | H90: P
A91: =IF(AND(D91="",D91=""),"",$D$3&"_"&ROW()-13-COUNTBLANK($D$14:D91)) -> Up_DB_54 | C91: 1. Thêm mới file đính kèm vào PYC vừa mới thêm mới thành công 2. Kiểm tra DB bảng REQUIREMENT_FILE_ATTACH select * from REQUIREMENT_FILE_ATTACH where REQUIREMENT_FORM_ID = '…ID của PYC đã thêm mới...' 3. Kiểm tra DB bảng CONTRACT_REQUIREMENT nếu người dùng upload loại file là Hợp đồng - hình thức Upload select * from CONTRACT_REQUIREMENT where REQUIREMENT_FORM_ID = '…ID của PYC đã thêm mới...' | D91: DB 2 bảng trả về dữ liệu đúng như đã thêm mới với từng file upload | E91: P | F91: P | G91: P | H91: P
A92: =IF(AND(D92="",D92=""),"",$D$3&"_"&ROW()-13-COUNTBLANK($D$14:D92)) -> Up_DB_55 | C92: 1. Thêm mới thành công 1 bản ghi vào Tab Khung chính sách 2. Kiểm tra DB bảng REQUIREMENT_POLICY select * from REQUIREMENT_FORM where REQUIREMENT_FORM_ID = '…ID của PYC nêu trên...' VD: 02-VAS/VTT-FTECH/BUNDLEDATA/887894336699AAAA | D92: DB trả về dữ liệu đúng như đã thêm mới | E92: P | F92: P | G92: P | H92: P
A93: =IF(AND(D93="",D93=""),"",$D$3&"_"&ROW()-13-COUNTBLANK($D$14:D93)) -> Up_DB_56 | C93: 1. Thêm mới thành công hình thức chia sẽ vào bản ghi khung chính sách mới đc thêm 2. Kiểm tra DB bảng REQUIREMENT_POLICY select * from REQUIREMENT_FORM where NAME = '…Tên PYC…' kiểm tra update trường SHARE_TYPE 3. KIỂM TRA DB bảng REQUIREMENT_POLICY_DETAIL select * from REQUIREMENT_POLICY_DETAIL where REQUIREMENT_POLICY_ID = '…ID của Policy đã thêm mới bên trên…' | D93: Bảng REQUIREMENT_POLICY cập nhật lại trường SHARE_TYPE đúng với giá trị đã quy định tương ứng với hình thức chia sẻ đã chọn Bảng REQUIREMENT_POLICY trả về dữ liệu đúng như đã thêm mới | E93: P | F93: P | G93: P | H93: P
A94: =IF(AND(D94="",D94=""),"",$D$3&"_"&ROW()-13-COUNTBLANK($D$14:D94)) -> Up_DB_57 | C94: 1. Thêm mới thành công 1 bản ghi vào Tab Nguồn dữ liệu 2. Kiểm tra DB bảng REQUIREMENT_DATASOURCE select * from REQUIREMENT_DATASOURCE where REQUIREMENT_FORM_ID = '…ID của PYC nêu trên...' | D94: DB trả về dữ liệu đúng như đã thêm mới | E94: P | F94: P | G94: P | H94: P
A95: =IF(AND(D95="",D95=""),"",$D$3&"_"&ROW()-13-COUNTBLANK($D$14:D95)) -> Up_DB_58 | C95: 1. Thực hiện Trình ký Voffice PYC đã tạo và gửi file để ký trên Voffice 2. Kiểm tra DB bảng REQUIREMENT_FORM select * from REQUIREMENT_FORM where REQUIREMENT_FORM_ID = '…ID của PYC nêu trên...' 3. Kiểm tra DB bảng REQUEST_FORM_VOFFICE select * from REQUEST_FORM_VOFFICE where REQUIREMENT_FORM_ID = '...ID của PYC nêu trên...' | D95: REQUIREMENT_FORM trả về dữ liệu được update dữ liệu vào trường VOFFICE_REPORT_ID và status = 1 -> 2 (Đang ký) REQUEST_FORM_VOFFICE trả về dữ liệu được hệ thống tự động thêm mới mapping VOFFICE_REPORT_ID với bản ghi REQUIREMENT_FORM | E95: P | F95: P | G95: P | H95: P
A96: =IF(AND(D96="",D96=""),"",$D$3&"_"&ROW()-13-COUNTBLANK($D$14:D96)) -> Up_DB_59 | C96: 1. Thực hiện ký thành công trên Voffice -> Hệ thống tự động xử lý các thông tin đẩy về HTĐS_VAS 2. Kiểm tra DB bảng REQUIREMENT_FORM select * from REQUIREMENT_FORM where REQUIREMENT_FORM_ID = '…ID của PYC nêu trên...' 3. Kiểm tra DB bảng REQUEST_FORM_VOFFICE select * from REQUEST_FORM_VOFFICE where REQUIREMENT_FORM_ID = '...ID của PYC nêu trên...' 4. Kiểm tra DB bảng CONTRACT_APPENDIX nếu upload loại file là HĐ và HĐ đã có trên hệ thống (thêm phụ lục HĐ) 5. Kiểm tra DB bảng CONTRACT nếu upload loại file là HĐ và HĐ chưa có trên hệ thống (tạo HĐ mới) | D96: REQUIREMENT_FORM trả về dữ liệu được update dữ liệu vào trường VOFFICE_REPORT_NO và status = 2 -> 3 (Đã ký) REQUEST_FORM_VOFFICE trả về dữ liệu được hệ thống tự động thêm mới mapping VOFFICE_REPORT_ID với bản ghi REQUIREMENT_FORM, stauts = 1 -> 2 DB Bảng CONTRACT_APPENDIX hoặc CONTRACT được thêm mới dữ liệu như action cũ gắn với CONTRACT_NO đã thêm đính kèm tại bảng REQUIREMENT_FILE_ATTACH và mapping với DOC_NO tại bảng này | E96: P | F96: P | G96: P | H96: P
B97: Các luồng chính của HTĐS_VAS dẫn tới sự kiện thay đổi dữ liệu lớn trong DB tại các bảng liên quan
A98: =IF(AND(D98="",D98=""),"",$D$3&"_"&ROW()-13-COUNTBLANK($D$14:D98)) -> Up_DB_60 | B98: Luồng ký biên bản Quản lý phí đầu số | C98: - Pre: Đã tổng hợp biên bản phí đầu số thành công Luồng xem biên bản phí đầu số và ký duyệt biên bản 1. Đăng nhập HTDS -> menu -> Quản lý phí đầu số -> Nhân viên đối soát duyệt 2. Tìm kiếm biên bản phí đầu số vừa tổng hợp - Nhập Loại chi phí: IMUZIK_NUMBER_FEE - Nhập kỳ muốn tổng hợp: 11/2025 3. Click [Duyệt] 4. Làm tương tự với các role khác theo luồng ký duyệt biên bản phí đầu số từ nhân viên phòng đối soát -> Nhân viên phòng đảm bảo doanh thu -> Lãnh đạo phòng đối soát -> Giám đốc TT ĐS (ký CA) -> Phòng tài chính nhận biên bản 5. Kiểm tra DB bảng IC_SC_COST_REPORT select * from IC_SC_COST_REPORT where TYPE_COST_ID = '...ID của loại chi phí đã nhập...' AND TIME_SUM = '01-nov-2025'; | D98: Hệ thống hiển thị thông tin biên bản tại Data grid Danh sách biên bản phí đầu số Click [Duyệt] -> hệ thống hiển thị popup Xem biên bản và có button [Ký] để người dùng Ký duyệt biên bản đang xem Với mỗi role ký DB trả về dữ liệu được update ở trường STATUS tương ứng với trạng thái của biên bản phí đầu số | E98: P | F98: P | G98: P | H98: P
A99: =IF(AND(D99="",D99=""),"",$D$3&"_"&ROW()-13-COUNTBLANK($D$14:D99)) -> Up_DB_61 | C99: Luồng Phòng tài chính nhận biên bản 1. Đăng nhập HTDS -> menu -> Quản lý phí đầu số -> phòng tài chính nhận biên bản 2. Tìm kiếm biên bản phí đầu số vừa tổng hợp - Nhập Loại chi phí: IMUZIK_NUMBER_FEE - Nhập kỳ muốn tổng hợp: 11/2025 3. Click [Duyệt] 4. Kiểm tra DB bảng IC_SC_COST_REPORT select * from IC_SC_COST_REPORT where TYPE_COST_ID = '...ID của loại chi phí đã nhập...' AND TIME_SUM = '01-nov-2025'; 5. Kiểm tra DB bảng IC_SC_COST_INVOICE select * from IC_SC_COST_INVOICE where IC_SC_COST_REPORT_ID = '...ID của biên bản tỏng bảng IC_SC_COST_REPORT...' | D99: Hệ thống hiển thị thông tin biên bản tại Data grid Danh sách biên bản phí đầu số Click [Duyệt] -> hệ thống hiển thị popup Xem biên bản và có button [Ký] để người dùng Ký duyệt biên bản đang xem DB trả về dữ liệu tại bảng IC_SC_COST_REPORT được update ở trường STATUS = 5 -> 6 DB trả về dữ liệu tại bảng IC_SC_COST_INVOICE với dữ liệu đúng với luồng cũ của hệ thống | E99: P | F99: P | G99: P | H99: P
A100: =IF(AND(D100="",D100=""),"",$D$3&"_"&ROW()-13-COUNTBLANK($D$14:D100)) -> Up_DB_62 | B100: Luồng ký biên bản chính thức | C100: - Pre: Đã tổng hợp dữ liệu đối soát VAS theo hợp đồng thành công Luồng Tổng hợp biên bản đối soát -> Tổng hợp biên bản đối soát thành công Luồng xem biên bản chính thức và ký duyệt biên bản 1. Đăng nhập HTDS -> menu -> Quản lý đối soát -> Quản lý biên bản đối soát chính thức -> Nhân viên đối soát xác nhận biên bản chính thức 2. Tìm kiếm biên bản chính thức vừa tổng hợp 3. Click [View report] -> Hiển thị popup Xem file -> Click [Ký] 4. Làm tương tự với các role khác theo luồng ký duyệt biên bản phí đầu số từ nhân viên phòng đối soát -> Nhân viên phòng đảm bảo doanh thu -> Lãnh đạo phòng đối soát -> Luồng ký của Đối tác trên PORTAL (3.6.4) ->Giám đốc TT ĐS (ký CA) -> Phòng tài chính nhận biên bản 5. Kiểm tra DB bảng IC_REPORT VÀ IC_REPORT_DETAIL | D100: Hệ thống hiển thị thông tin biên bản tại Data grid Danh sách biên bản Click [Duyệt] -> hệ thống hiển thị popup Xem biên bản và có button [Ký] để người dùng Ký duyệt biên bản đang xem Với mỗi role ký DB trả về dữ liệu tại bảng IC_REPORT được update ở trường STATUS tương ứng với trạng thái của biên bản chính thức. Dữ liệu tại bảng IC_REPORT_DETAIL không bị thay đổi | E100: P | F100: P | G100: P | H100: P
A101: =IF(AND(D101="",D101=""),"",$D$3&"_"&ROW()-13-COUNTBLANK($D$14:D101)) -> Up_DB_63 | C101: Luồng Phòng tài chính nhận biên bản 1. Đăng nhập HTDS -> menu -> Quản lý đối soát -> Quản lý biên bản đối soát chính thức -> Tài chính xem và thanh toán biên bản chính thức 2. Tìm kiếm biên bản chính thức vừa tổng hợp 3. Click [View report] -> Hiển thị popup Xem file -> Click [Ký] 4. Kiểm tra DB bảng IC_REPORT 5. Kiểm tra DB bảng IC_INVOICE và IC_INVOICE_DETAIL | D101: Hệ thống hiển thị thông tin biên bản tại Data grid Danh sách biên bản Click [Duyệt] -> hệ thống hiển thị popup Xem biên bản và có button [Ký] để người dùng Ký duyệt biên bản đang xem DB trả về dữ liệu tại bảng IC_REPORT được update ở trường STATUS = 8 -> 9 DB trả về dữ liệu tại bảng IC_INVOICE và IC_INVOICE_DETAIL với dữ liệu đúng với luồng cũ của hệ thống | E101: P | F101: P | G101: P | H101: P
A102: =IF(AND(D102="",D102=""),"",$D$3&"_"&ROW()-13-COUNTBLANK($D$14:D102)) -> Up_DB_64 | B102: Luồng ký biên bản Đơn vị ngoài | C102: - Pre: Đã tổng hợp dữ liệu đối soát VAS theo hợp đồng thành công Luồng Tổng hợp biên bản đối soát -> Tổng hợp biên bản đối soát thành công Luồng xem biên bản đối soát và ký duyệt biên bản 1. Đăng nhập HTDS -> menu -> Quản lý đối soát -> Quản lý biên bản đối soát chính thức -> Nhân viên đối soát xác nhận biên bản chính thức 2. Tìm kiếm biên bản chính thức vừa tổng hợp 3. Click [View report] -> Hiển thị popup Xem file -> Click [Ký] 4. Làm tương tự với các role khác theo luồng ký duyệt biên bản đối soát từ nhân viên phòng đối soát -> Nhân viên phòng đảm bảo doanh thu -> (Lãnh đạo phòng ĐBDT) -> Lãnh đạo phòng đối soát 5. Kiểm tra ĐB bảng IC_REPORT và IC_REPORT_DETAIL | D102: Hệ thống hiển thị thông tin biên bản tại Data grid Danh sách biên bản Click [Duyệt] -> hệ thống hiển thị popup Xem biên bản và có button [Ký] để người dùng Ký duyệt biên bản đang xem Với mỗi role ký DB trả về dữ liệu tại bảng IC_REPORT được update ở trường STATUS tương ứng với trạng thái của biên bản đối soát. Dữ liệu tại bảng IC_REPORT_DETAIL không bị thay đổi | E102: P | F102: P | G102: P | H102: P
...
